macrobond_data_api/__init__.py
macrobond_data_api/__version__.py
macrobond_data_api/_generated.py
macrobond_data_api/_get_api.py
macrobond_data_api/py.typed
macrobond_data_api/com/__init__.py
macrobond_data_api/com/_com_api_in_house_series.py
macrobond_data_api/com/_com_api_metadata.py
macrobond_data_api/com/_com_api_revision.py
macrobond_data_api/com/_com_api_search.py
macrobond_data_api/com/_com_api_series.py
macrobond_data_api/com/_error_message_to_status_code.py
macrobond_data_api/com/_fix_datetime.py
macrobond_data_api/com/_metadata_directory.py
macrobond_data_api/com/com_api.py
macrobond_data_api/com/com_client.py
macrobond_data_api/com/com_types/__init__.py
macrobond_data_api/com/com_types/connection.py
macrobond_data_api/com/com_types/database.py
macrobond_data_api/com/com_types/entity.py
macrobond_data_api/com/com_types/metadata.py
macrobond_data_api/com/com_types/metadata_information.py
macrobond_data_api/com/com_types/search_query.py
macrobond_data_api/com/com_types/search_result.py
macrobond_data_api/com/com_types/series.py
macrobond_data_api/com/com_types/series_expression.py
macrobond_data_api/com/com_types/series_request.py
macrobond_data_api/com/com_types/series_with_revisions.py
macrobond_data_api/common/__init__.py
macrobond_data_api/common/api.py
macrobond_data_api/common/client.py
macrobond_data_api/common/enums/__init__.py
macrobond_data_api/common/enums/calendar_date_mode.py
macrobond_data_api/common/enums/calendar_merge_mode.py
macrobond_data_api/common/enums/metadata_attribute_type.py
macrobond_data_api/common/enums/release_event_item_kind.py
macrobond_data_api/common/enums/series_frequency.py
macrobond_data_api/common/enums/series_missing_value_method.py
macrobond_data_api/common/enums/series_partial_periods_method.py
macrobond_data_api/common/enums/series_to_higher_frequency_method.py
macrobond_data_api/common/enums/series_to_lower_frequency_method.py
macrobond_data_api/common/enums/series_weekdays.py
macrobond_data_api-3.0.3.dist-info/licenses/LICENSE
macrobond_data_api-3.0.3.dist-info/METADATA
macrobond_data_api-3.0.3.dist-info/WHEEL
macrobond_data_api-3.0.3.dist-info/top_level.txt
macrobond_data_api-3.0.3.dist-info/RECORD
