Metadata-Version: 2.4
Name: macrobond-data-api
Version: 3.0.3
Summary: Exposes a common API in Python for the Macrobond Web and Client Data APIs
Home-page: https://github.com/macrobond/macrobond-data-api
Author: Macrobond Financial
Author-email: support@macrobond.com
Project-URL: Documentation, https://macrobond.github.io/macrobond-data-api
Project-URL: Source, https://github.com/macrobond/macrobond-data-api
Project-URL: Tracker, https://github.com/macrobond/macrobond-data-api/issues
Classifier: License :: OSI Approved :: MIT License
Classifier: Programming Language :: Python :: 3 :: Only
Classifier: Programming Language :: Python :: 3
Classifier: Programming Language :: Python :: 3.9
Requires-Python: >=3.9
License-File: LICENSE
Requires-Dist: keyring>=25.6.0
Requires-Dist: requests>=2.32.3
Requires-Dist: ijson>=3.3.0
Requires-Dist: pywin32>=310; os_name == "nt"
Provides-Extra: extra
Requires-Dist: matplotlib; extra == "extra"
Requires-Dist: statsmodels; extra == "extra"
Requires-Dist: scikit-learn; extra == "extra"
Requires-Dist: pandas; extra == "extra"
Provides-Extra: dev
Requires-Dist: mypy==1.15.0; extra == "dev"
Requires-Dist: pylint==3.3.7; extra == "dev"
Requires-Dist: pycodestyle==2.13.0; extra == "dev"
Requires-Dist: pdoc3==0.10.0; extra == "dev"
Requires-Dist: build==1.2.2.post1; extra == "dev"
Requires-Dist: pytest==8.3.5; extra == "dev"
Requires-Dist: pytest-xdist==3.6.1; extra == "dev"
Requires-Dist: coverage==7.8.0; extra == "dev"
Requires-Dist: black[jupyter]==25.1.0; extra == "dev"
Requires-Dist: requests[socks]>=2.32.3; extra == "dev"
Requires-Dist: nbconvert==7.16.6; extra == "dev"
Requires-Dist: ipython>=7.34.0; extra == "dev"
Requires-Dist: types-pywin32==310.0.0.20250429; extra == "dev"
Requires-Dist: types-requests==2.32.0.20250328; extra == "dev"
Requires-Dist: types-setuptools==80.3.0.20250505; extra == "dev"
Requires-Dist: filelock==3.18.0; extra == "dev"
Requires-Dist: numpy>=1.24.4; extra == "dev"
Provides-Extra: socks
Requires-Dist: requests[socks]>=2.32.3; extra == "socks"
Dynamic: author
Dynamic: author-email
Dynamic: classifier
Dynamic: description
Dynamic: description-content-type
Dynamic: home-page
Dynamic: license-file
Dynamic: project-url
Dynamic: provides-extra
Dynamic: requires-dist
Dynamic: requires-python
Dynamic: summary
